excal/.__main__.py.~undo-tree~
excal/__init__.py
excal/__main__.py
excal/analyzer.py
excal/astNode.py
excal/cwalker.py
excal/offence.py
excal/output.py
excal/pluginManager.py
excal/visitor.py
excal-0.0.19.dist-info/LICENSE
excal-0.0.19.dist-info/METADATA
excal-0.0.19.dist-info/WHEEL
excal-0.0.19.dist-info/entry_points.txt
excal-0.0.19.dist-info/top_level.txt
excal-0.0.19.dist-info/RECORD
