Metadata-Version: 2.1
Name: excal
Version: 0.0.19
Summary: Extendable Clang AST based c/c++ linter
Home-page: https://github.com/PKN-AUTDE/excal
Download-URL: https://github.com/PKN-AUTDE/excal/archive/refs/tags/v_0_0_12.tar.gz
Author: Benedikt Kehrein
Author-email: b.kehrein@reply.de
License: lgpl 2.1
Platform: UNKNOWN
Classifier: Programming Language :: Python :: 3
Classifier: Operating System :: OS Independent
Requires-Python: >=3.6
License-File: LICENSE
Requires-Dist: libclang
